{
  "menu": [
    {
      "name": "Dashboards",
      "badge": "2",
      "badgeClass": "badge badge-light-warning badge-pill ml-auto mr-1",
      "icon": "home",
      "slug": "",
      "submenu": [
        {
          "url": "admin/dashboard/analytics",
          "name": "Analytics",
          "icon": "circle",
          "slug": "dashboard-analytics"
        },
        {
          "url": "admin/dashboard/ecommerce",
          "name": "eCommerce",
          "icon": "circle",
          "slug": "dashboard-ecommerce"
        }
      ]
    },
    {
      "navheader": "Table",
      "slug": ""
    },
    {
      "name": "User",
      "badgeClass": "badge badge-light-warning badge-pill ml-auto mr-1",
      "icon": "user",
      "slug": "User",
      "url": "admin/users/user-list"
    },
    {
      "navheader": "Soporte",
      "slug": ""
    },
    {
      "name": "Tickets",
      "badgeClass": "badge badge-light-warning badge-pill ml-auto mr-1",
      "icon": "tag",
      "slug": "Tickets",
      "url": "admin/tickets/list-admin"
    }
  ]
}
